CHANGES.txt
MANIFEST.in
README.txt
TODO.txt
ZPL.txt
setup.cfg
setup.py
src/pypimirror/README.txt
src/pypimirror/__init__.py
src/pypimirror/logger.py
src/pypimirror/mirror.py
src/pypimirror/pypimirror.cfg.sample
src/pypimirror/tests.py
src/pypimirror/util.py
src/pypimirror.egg-info/PKG-INFO
src/pypimirror.egg-info/SOURCES.txt
src/pypimirror.egg-info/dependency_links.txt
src/pypimirror.egg-info/entry_points.txt
src/pypimirror.egg-info/not-zip-safe
src/pypimirror.egg-info/requires.txt
src/pypimirror.egg-info/top_level.txt
src/z3c/__init__.py
src/z3c.pypimirror.egg-info/SOURCES.txt
src/z3c.pypimirror.egg-info/dependency_links.txt
src/z3c.pypimirror.egg-info/entry_points.txt
src/z3c.pypimirror.egg-info/namespace_packages.txt
src/z3c.pypimirror.egg-info/requires.txt
src/z3c.pypimirror.egg-info/top_level.txt
src/z3c/pypimirror/__init__.py
src/z3c/pypimirror/logger.py
src/z3c/pypimirror/mirror.py
src/z3c/pypimirror/tests.py
src/z3c/pypimirror/util.py